{
  "_fv": 5,
  "_type": "recipe",
  "definition": {
    "recipeType": "Crafting",
    "recipeRetstackSize": 1,
    "recipeShapeless": false,
    "recipeReturnStack": {
      "value": "CUSTOM:BlackSkin"
    },
    "recipeSlots": [
      {
        "value": "Items.ROTTEN_FLESH"
      },
      {
        "value": "CUSTOM:CompressedHexadorium"
      },
      {
        "value": "Items.ROTTEN_FLESH"
      },
      {
        "value": "Items.ROTTEN_FLESH"
      },
      {
        "value": "Items.DYE#0"
      },
      {
        "value": "Items.ROTTEN_FLESH"
      },
      {
        "value": "Items.ROTTEN_FLESH"
      },
      {
        "value": "CUSTOM:Hexadorium"
      },
      {
        "value": "Items.ROTTEN_FLESH"
      }
    ],
    "smeltingXPReward": 0.0,
    "smeltingRetstackSize": 1,
    "name": "blackskinrecipe",
    "namespace": "mod"
  }
}